ChemMod/__init__.py
ChemMod/__main__.py
ChemMod/content/ChemMod.py
ChemMod/content/__init__.py
ChemMod/demo/__init__.py
ChemMod/demo/_plot.py
ChemMod/demo/_pxrd.py
ChemMod/equation/_M.py
ChemMod/equation/__init__.py
ChemMod/equation/_element_data.py
ChemMod/equation/_equilibrium.py
ChemMod/experiment/__init__.py
ChemMod/help/__init__.py
ChemMod/help/_content.py
ChemMod/help/_content_data.py
ChemMod/help/_info.py
ChemMod/plot/__init__.py
ChemMod/plot/_arrhenius_plot.py
ChemMod/plot/_bjerrum_plot.py
ChemMod/plot/_gibbs_plot.py
ChemMod/plot/_order_plot.py
ChemMod/plot/_theme.py
ChemMod/plot/_theme_data.py
ChemMod/plot/_theme_list_for_formatting_of_plots.py
ChemMod/plot/_titration_plot.py
ChemMod-0.0.20.dist-info/COPYING.txt
ChemMod-0.0.20.dist-info/LICENSE.txt
ChemMod-0.0.20.dist-info/METADATA
ChemMod-0.0.20.dist-info/WHEEL
ChemMod-0.0.20.dist-info/top_level.txt
ChemMod-0.0.20.dist-info/RECORD
