Metadata-Version: 2.1
Name: ChemMod
Version: 0.0.20
Summary: Python program for practical plotting and calculation in chemistry. ChemMod is developed as a userfriendly python package for chemistry students. The package contains a variety of different useful plot functions and formula functions from chemistry e.g. buffer diagrams, Gibbs-energy functions and regression tools.
Author-email: August Jacobi <chemistry.chem.mod@gmail.com>
Project-URL: Homepage, https://www.facebook.com/groups/1241482943732179
Classifier: Programming Language :: Python :: 3
Classifier: License :: OSI Approved :: GNU General Public License v3 or later (GPLv3+)
Classifier: Operating System :: OS Independent
Requires-Python: >=3.9
License-File: LICENSE.txt
License-File: COPYING.txt
